MANIFEST.in
README.md
pyproject.toml
setup.py
include/mathutils/funs.hpp
include/mathutils/lookup_tables.hpp
mathutils/__init__.py
pymathutils_wlough.egg-info/PKG-INFO
pymathutils_wlough.egg-info/SOURCES.txt
pymathutils_wlough.egg-info/dependency_links.txt
pymathutils_wlough.egg-info/not-zip-safe
pymathutils_wlough.egg-info/requires.txt
pymathutils_wlough.egg-info/top_level.txt
src/cpp/bindings.cpp